{
  "users": [
    {
      "email": "demo@gsffc.org",
      "password": "gsf2026",
      "name": "Demo会员",
      "position": "MF",
      "joined": "2024-01-15"
    },
    {
      "email": "donglin@gsffc.org",
      "password": "gsf2026",
      "name": "Donglin",
      "position": "FW",
      "joined": "2023-08-20"
    },
    {
      "email": "dike@gsffc.org",
      "password": "gsf2026",
      "name": "狄克",
      "position": "FW",
      "joined": "2022-03-01"
    },
    {
      "email": "kevin@gsffc.org",
      "password": "gsf2026",
      "name": "Kevin",
      "position": "CAM",
      "joined": "2022-05-12"
    },
    {
      "email": "lifeng@gsffc.org",
      "password": "gsf2026",
      "name": "李峰",
      "position": "ST",
      "joined": "2022-06-30"
    },
    {
      "email": "yangfan@gsffc.org",
      "password": "gsf2026",
      "name": "杨帆",
      "position": "LM",
      "joined": "2022-04-18"
    }
  ],
  "events": [
    {
      "id": "6a2a24a22e8d92aecd66b520",
      "title": "周六例行训练赛 11v11",
      "date": "2026-06-13",
      "time": "16:00 - 18:00",
      "location": "2065 Tarob Ct, Milpitas, CA 95035",
      "coords": {
        "lat": 37.4045892,
        "lng": -121.8907831
      },
      "description": "本周六例行训练赛，11人制对抗。请穿好球鞋护腿板，自带水。报名截止周五晚10点，人数不足改为小场。",
      "capacity": 22,
      "signups": [
        "dike@gsffc.org",
        "kevin@gsffc.org",
        "lifeng@gsffc.org",
        "demo@gsffc.org",
        "donglin@gsffc.org"
      ],
      "comments": [
        {
          "author": "狄克",
          "time": "2026-06-09 21:30",
          "text": "这周有联赛对手来踩场，大家踊跃报名！"
        },
        {
          "author": "Kevin",
          "time": "2026-06-10 08:12",
          "text": "+1 已报，求带一脚出球中卫"
        }
      ],
      "checkins": []
    },
    {
      "id": "7b3c35b33f9ea3bfde77c631",
      "title": "每周杯大乱斗 Online",
      "date": "2026-06-17",
      "time": "20:00 - 22:00",
      "location": "线上 (FIFA / 实况)",
      "coords": null,
      "description": "每周三晚线上大乱斗，赛制视报名人数定。冠军获微信群专属头衔一周。",
      "capacity": 16,
      "signups": [
        "yangfan@gsffc.org"
      ],
      "comments": []
    },
    {
      "id": "8c4d46c44a0fb4caef88d742",
      "title": "校联杯小组赛 GSF vs SBK",
      "date": "2026-06-20",
      "time": "14:00 - 16:00",
      "location": "Stanford IM Field",
      "coords": {
        "lat": 37.43053,
        "lng": -122.15917
      },
      "description": "校联杯小组赛第二轮，对阵老对手SBK。赛前30分钟到场热身，统一主场白色球衣。",
      "capacity": 18,
      "signups": [
        "dike@gsffc.org",
        "lifeng@gsffc.org"
      ],
      "comments": [
        {
          "author": "李峰",
          "time": "2026-06-08 19:05",
          "text": "克星属性拉满，这场必须赢"
        }
      ]
    },
    {
      "id": "5f1b13a11d7c81aabc55a409",
      "title": "赛季总结烧烤聚会",
      "date": "2026-05-30",
      "time": "12:00 - 15:00",
      "location": "Cuesta Park, Mountain View",
      "coords": {
        "lat": 37.37758,
        "lng": -122.06965
      },
      "description": "春季赛季总结+烧烤，家属欢迎。俱乐部提供肉和饮料，可自带拿手菜。",
      "capacity": 40,
      "signups": [
        "dike@gsffc.org",
        "kevin@gsffc.org",
        "yangfan@gsffc.org",
        "donglin@gsffc.org"
      ],
      "comments": []
    }
  ]
}